collective.exportimport-1.15-py3.12-nspkg.pth
collective/exportimport/__init__.py
collective/exportimport/config.py
collective/exportimport/configure.zcml
collective/exportimport/deserializer.py
collective/exportimport/export_content.py
collective/exportimport/export_other.py
collective/exportimport/export_topic.py
collective/exportimport/fix_html.py
collective/exportimport/import_content.py
collective/exportimport/import_other.py
collective/exportimport/interfaces.py
collective/exportimport/permissions.zcml
collective/exportimport/serializer.py
collective/exportimport/testing.py
collective/exportimport/locales/README.rst
collective/exportimport/locales/__init__.py
collective/exportimport/locales/collective.exportimport.pot
collective/exportimport/locales/update.py
collective/exportimport/locales/update.sh
collective/exportimport/locales/en/LC_MESSAGES/collective.exportimport.po
collective/exportimport/locales/es/LC_MESSAGES/collective.exportimport.po
collective/exportimport/templates/export_content.pt
collective/exportimport/templates/export_other.pt
collective/exportimport/templates/import_content.pt
collective/exportimport/templates/import_defaultpages.pt
collective/exportimport/templates/import_discussion.pt
collective/exportimport/templates/import_localroles.pt
collective/exportimport/templates/import_members.pt
collective/exportimport/templates/import_ordering.pt
collective/exportimport/templates/import_portlets.pt
collective/exportimport/templates/import_redirects.pt
collective/exportimport/templates/import_relations.pt
collective/exportimport/templates/import_translations.pt
collective/exportimport/templates/links.pt
collective/exportimport/tests/__init__.py
collective/exportimport/tests/file.pdf
collective/exportimport/tests/test_drop_and_include.py
collective/exportimport/tests/test_export.py
collective/exportimport/tests/test_fix_html.py
collective/exportimport/tests/test_import.py
collective/exportimport/tests/test_setup.py
collective.exportimport-1.15.dist-info/LICENSE.GPL
collective.exportimport-1.15.dist-info/LICENSE.rst
collective.exportimport-1.15.dist-info/METADATA
collective.exportimport-1.15.dist-info/WHEEL
collective.exportimport-1.15.dist-info/entry_points.txt
collective.exportimport-1.15.dist-info/namespace_packages.txt
collective.exportimport-1.15.dist-info/top_level.txt
collective.exportimport-1.15.dist-info/RECORD
