Metadata-Version: 2.1
Name: collective.exportimport
Version: 1.15
Summary: An add-on for Plone to Export and import content, members, relations, translations and localroles.
Home-page: https://github.com/collective/collective.exportimport
Author: Philip Bauer (for starzel.de)
Author-email: info@starzel.de
License: GPL version 2
Project-URL: PyPI, https://pypi.python.org/pypi/collective.exportimport
Project-URL: Source, https://github.com/collective/collective.exportimport
Project-URL: Tracker, https://github.com/collective/collective.exportimport/issues
Project-URL: Documentation, https://github.com/collective/collective.exportimport#readme
Keywords: Python Plone CMS
Classifier: Development Status :: 5 - Production/Stable
Classifier: Intended Audience :: Developers
Classifier: Environment :: Web Environment
Classifier: Framework :: Plone
Classifier: Framework :: Plone :: Addon
Classifier: Framework :: Plone :: 4.3
Classifier: Framework :: Plone :: 5.0
Classifier: Framework :: Plone :: 5.1
Classifier: Framework :: Plone :: 5.2
Classifier: Framework :: Plone :: 6.0
Classifier: Programming Language :: Python
Classifier: Programming Language :: Python :: 2.7
Classifier: Programming Language :: Python :: 3.7
Classifier: Programming Language :: Python :: 3.8
Classifier: Programming Language :: Python :: 3.9
Classifier: Programming Language :: Python :: 3.10
Classifier: Programming Language :: Python :: 3.11
Classifier: Operating System :: OS Independent
Classifier: License :: OSI Approved :: GNU General Public License v2 (GPLv2)
Requires-Python: >=2.7, !=3.0.*, !=3.1.*, !=3.2.*, !=3.3.*, !=3.4.*, !=3.5.*
License-File: LICENSE.GPL
License-File: LICENSE.rst
Requires-Dist: hurry.filesize
Requires-Dist: setuptools
Requires-Dist: six
Requires-Dist: beautifulsoup4
Requires-Dist: ijson
Requires-Dist: plone.api>=1.8.4
Requires-Dist: plone.restapi
Provides-Extra: test
Requires-Dist: plone.app.testing; extra == "test"
Requires-Dist: plone.app.robotframework; extra == "test"
Requires-Dist: plone.app.contenttypes; extra == "test"
